MANIFEST.in
setup.py
models/__init__.py
models/mysql/__init__.py
models/mysql/test.py
models/postgresql_1/__init__.py
models/postgresql_1/postgres.py
quickdb/README.md
quickdb/__init__.py
quickdb/conn_kafka.py
quickdb/conn_mongo.py
quickdb/conn_redis.py
quickdb.egg-info/PKG-INFO
quickdb.egg-info/SOURCES.txt
quickdb.egg-info/dependency_links.txt
quickdb.egg-info/requires.txt
quickdb.egg-info/top_level.txt
quickdb/mysql/__init__.py
quickdb/mysql/orm/__init__.py
quickdb/mysql/orm/sqlalchemy/__init__.py
quickdb/mysql/orm/sqlalchemy/engine.py
quickdb/orm/__init__.py
quickdb/orm/sqlalchemy/__init__.py
quickdb/orm/sqlalchemy/engine.py
quickdb/orm/sqlalchemy/exception.py
quickdb/postgresql/__init__.py
quickdb/postgresql/orm/__init__.py
quickdb/postgresql/orm/sqlalchemy/__init__.py
quickdb/postgresql/orm/sqlalchemy/engine.py